{
  "version": 2.0,
  "questions": [
    {
      "question": "1.Which of the following methods can be successfully used for the cultivation of virus?:",
      "answers": {
        "a": "Inoculation into eggs",
        "b": "Inoculation into embryonated eggs",
        "c": "Inoculation into human volunteers",
        "d": "All of the above"
      },
      
      "correctAnswer": "b",
      "difficulty": "beginner"
    },
    {
      "question": "2.Which of the following provide chemical, biological and antigenic properties to virus ?",
      "answers": {
        "a": "Virion",
        "b": "Envelope",
        "c": "Capsid",
        "d": "Nucleocapsid"
      },
      
      "correctAnswer": "b",
      "difficulty": "beginner"
    },

    {
      "question": "3.Viral growth and multiplication in the egg embryo is indicated by-------",
      "answers": {
        "a": "Death of the embryo",
        "b": "Cell damage",
        "c": "Formation of typical lesions",
        "d": "All the above"
      },
          
      "correctAnswer": "d",
      "difficulty": "beginner"
    },

      {
        "question": "4.Routes of viral inoculation in embryonated eggs include:",
        "answers": {
          "a": "Intradermal inoculation",
          "b": "Allantoic cavity inoculation",
          "c": "Intraperitoneal inoculation",
          "d": "None of the above"
        },

            
      "correctAnswer": "b",
      "difficulty": "beginner"
    }   
     
    
  ]
}
